telegramchatbotproject/api_key.py
telegramchatbotproject/appointment.py
telegramchatbotproject/appointment_handler.py
telegramchatbotproject/appointment_session.py
telegramchatbotproject/base_valaszok.py
telegramchatbotproject/kerdes.py
telegramchatbotproject/main.py
telegramchatbotproject/panasz.py
telegramchatbotproject/panasz_session.py
telegramchatbotproject/szam_jatek.py
TelegramChatbotProject-1.0.1.dist-info/METADATA
TelegramChatbotProject-1.0.1.dist-info/WHEEL
TelegramChatbotProject-1.0.1.dist-info/top_level.txt
TelegramChatbotProject-1.0.1.dist-info/RECORD
