Metadata-Version: 2.1
Name: TelegramChatbotProject
Version: 1.0.1
Summary: Telegram chatbot with added functions
Home-page: https://github.com/MitykoNorbert/TelegramChatbot
Author: MitykoNorbert
Author-email: norbert.mityko001@gmail.com
License: UNKNOWN
Platform: UNKNOWN
